kml_analysis_pkg/__init__.py
kml_analysis_pkg/author_contribution/__init__.py
kml_analysis_pkg/author_para_contribution/__init__.py
kml_analysis_pkg/controversy/__init__.py
kml_analysis_pkg/downloader_featured/__init__.py
kml_analysis_pkg/downloader_from_titles/__init__.py
kml_analysis_pkg/external_gaps/__init__.py
kml_analysis_pkg/external_gaps/algorithm.py
kml_analysis_pkg/external_gaps/start_segmentation.py
kml_analysis_pkg/external_gaps/tools.py
kml_analysis_pkg/internal_gaps/__init__.py
kml_analysis_pkg/internal_gaps/algorithm.py
kml_analysis_pkg/internal_gaps/tools.py
kml_analysis_parasKumarSahu-0.1.1.dist-info/LICENSE
kml_analysis_parasKumarSahu-0.1.1.dist-info/METADATA
kml_analysis_parasKumarSahu-0.1.1.dist-info/WHEEL
kml_analysis_parasKumarSahu-0.1.1.dist-info/top_level.txt
kml_analysis_parasKumarSahu-0.1.1.dist-info/RECORD
