Metadata-Version: 2.1
Name: kml-analysis-parasKumarSahu
Version: 0.1.1
Summary: Wikipedia Analysis Toolkit
Home-page: https://github.com/parasKumarSahu/Knolml-Analysis-Package
Author: Paras Kumar
Author-email: paraskumardavhehal1@gmail.com
License: UNKNOWN
Platform: UNKNOWN
Classifier: Programming Language :: Python :: 3
Classifier: License :: OSI Approved :: MIT License
Classifier: Operating System :: OS Independent
Requires-Python: >=3.6
